pymontecarlo_casino2/__init__.py
pymontecarlo_casino2/_version.py
pymontecarlo_casino2/conftest.py
pymontecarlo_casino2/expander.py
pymontecarlo_casino2/exporter.py
pymontecarlo_casino2/importer.py
pymontecarlo_casino2/program.py
pymontecarlo_casino2/program_gui.py
pymontecarlo_casino2/test__init__.py
pymontecarlo_casino2/test_exporter.py
pymontecarlo_casino2/test_importer.py
pymontecarlo_casino2/test_program.py
pymontecarlo_casino2/test_worker.py
pymontecarlo_casino2/worker.py
pymontecarlo_casino2/casino2/UserLayers.txt
pymontecarlo_casino2/casino2/update.txt
pymontecarlo_casino2/casino2/wincasino2.exe
pymontecarlo_casino2/casino2/wincasino2_64.exe
pymontecarlo_casino2/casino2/wincasino_logging_debug.log
pymontecarlo_casino2/casino2/Settings/README.txt
pymontecarlo_casino2/casino2/int/KCOEFF.PRN
pymontecarlo_casino2/casino2/int/LCOEFF.PRN
pymontecarlo_casino2/casino2/int/LINES.DON
pymontecarlo_casino2/casino2/int/RAC.R
pymontecarlo_casino2/casino2/int/RAC.TOT
pymontecarlo_casino2/casino2/int/RAG.R
pymontecarlo_casino2/casino2/int/RAG.TOT
pymontecarlo_casino2/casino2/int/RAL.PAR
pymontecarlo_casino2/casino2/int/RAL.R
pymontecarlo_casino2/casino2/int/RAL.TOT
pymontecarlo_casino2/casino2/int/RAR.R
pymontecarlo_casino2/casino2/int/RAR.TOT
pymontecarlo_casino2/casino2/int/RAS.R
pymontecarlo_casino2/casino2/int/RAS.TOT
pymontecarlo_casino2/casino2/int/RAT.R
pymontecarlo_casino2/casino2/int/RAT.TOT
pymontecarlo_casino2/casino2/int/RAUDD.R
pymontecarlo_casino2/casino2/int/RBA.R
pymontecarlo_casino2/casino2/int/RBA.TOT
pymontecarlo_casino2/casino2/int/RBB.R
pymontecarlo_casino2/casino2/int/RBB.TOT
pymontecarlo_casino2/casino2/int/RBE.R
pymontecarlo_casino2/casino2/int/RBE.TOT
pymontecarlo_casino2/casino2/int/RBI.R
pymontecarlo_casino2/casino2/int/RBI.TOT
pymontecarlo_casino2/casino2/int/RBR.R
pymontecarlo_casino2/casino2/int/RBR.TOT
pymontecarlo_casino2/casino2/int/RCA.R
pymontecarlo_casino2/casino2/int/RCA.TOT
pymontecarlo_casino2/casino2/int/RCC.R
pyMonteCarlo_Casino2-1.1.0.dist-info/LICENSE
pyMonteCarlo_Casino2-1.1.0.dist-info/METADATA
pyMonteCarlo_Casino2-1.1.0.dist-info/WHEEL
pyMonteCarlo_Casino2-1.1.0.dist-info/top_level.txt
pyMonteCarlo_Casino2-1.1.0.dist-info/RECORD
